{
  "main": {
    "id": "bca88a3f2d5ad5a2",
    "type": "split",
    "children": [
      {
        "id": "d3449b53e536b333",
        "type": "tabs",
        "children": [
          {
            "id": "ee2f6d266474ad88",
            "type": "leaf",
            "state": {
              "type": "empty",
              "state": {},
              "icon": "lucide-file",
              "title": "New tab"
            }
          }
        ]
      }
    ],
    "direction": "vertical"
  },
  "left": {
    "id": "f1d465df32cd7583",
    "type": "split",
    "children": [
      {
        "id": "375492a521530402",
        "type": "tabs",
        "children": [
          {
            "id": "79d99b53da49dd6b",
            "type": "leaf",
            "state": {
              "type": "file-explorer",
              "state": {
                "sortOrder": "alphabetical",
                "autoReveal": false
              },
              "icon": "lucide-folder-closed",
              "title": "Files"
            }
          },
          {
            "id": "577771a6ab15c3fc",
            "type": "leaf",
            "state": {
              "type": "search",
              "state": {
                "query": "",
                "matchingCase": false,
                "explainSearch": false,
                "collapseAll": false,
                "extraContext": false,
                "sortOrder": "alphabetical"
              },
              "icon": "lucide-search",
              "title": "Search"
            }
          },
          {
            "id": "94cccf6277a7f1a2",
            "type": "leaf",
            "state": {
              "type": "bookmarks",
              "state": {},
              "icon": "lucide-bookmark",
              "title": "Bookmarks"
            }
          }
        ]
      }
    ],
    "direction": "horizontal",
    "width": 300
  },
  "right": {
    "id": "63319bc5368cf299",
    "type": "split",
    "children": [
      {
        "id": "ff865f5a1f77b0c3",
        "type": "tabs",
        "children": [
          {
            "id": "440ec340c01446f5",
            "type": "leaf",
            "state": {
              "type": "backlink",
              "state": {
                "file": "Jednoobszarowy OSPF/Bazy danych OSPF.md",
                "collapseAll": false,
                "extraContext": false,
                "sortOrder": "alphabetical",
                "showSearch": false,
                "searchQuery": "",
                "backlinkCollapsed": false,
                "unlinkedCollapsed": true
              },
              "icon": "links-coming-in",
              "title": "Backlinks for Bazy danych OSPF"
            }
          },
          {
            "id": "2fb7200eb6aa11f9",
            "type": "leaf",
            "state": {
              "type": "outgoing-link",
              "state": {
                "file": "Jednoobszarowy OSPF/Bazy danych OSPF.md",
                "linksCollapsed": false,
                "unlinkedCollapsed": true
              },
              "icon": "links-going-out",
              "title": "Outgoing links from Bazy danych OSPF"
            }
          },
          {
            "id": "0424701f7fe2b0d1",
            "type": "leaf",
            "state": {
              "type": "tag",
              "state": {
                "sortOrder": "frequency",
                "useHierarchy": true,
                "showSearch": false,
                "searchQuery": ""
              },
              "icon": "lucide-tags",
              "title": "Tags"
            }
          },
          {
            "id": "ea1e1c2ed8a6ee96",
            "type": "leaf",
            "state": {
              "type": "outline",
              "state": {
                "file": "Jednoobszarowy OSPF/Bazy danych OSPF.md",
                "followCursor": false,
                "showSearch": false,
                "searchQuery": ""
              },
              "icon": "lucide-list",
              "title": "Outline of Bazy danych OSPF"
            }
          }
        ]
      }
    ],
    "direction": "horizontal",
    "width": 300,
    "collapsed": true
  },
  "left-ribbon": {
    "hiddenItems": {
      "switcher:Open quick switcher": false,
      "graph:Open graph view": false,
      "canvas:Create new canvas": false,
      "daily-notes:Open today's daily note": false,
      "templates:Insert template": false,
      "command-palette:Open command palette": false
    }
  },
  "active": "ee2f6d266474ad88",
  "lastOpenFiles": [
    "ACL/Nazwane rozszerzone listy ACL.md",
    "Pasted image 20250512191411.png",
    "ACL/Nazwane standardowe listy ACL.md",
    "ACL/Established TCP.md",
    "Pasted image 20250512184141.png",
    "Pasted image 20250512184021.png",
    "ACL/Numerowane rozszerzone listy ACL.md",
    "Pasted image 20250512183609.png",
    "Pasted image 20250512183503.png",
    "ACL/Numerowane standardowe listy ACL.md",
    "ACL/Rozszerzone ACL.md",
    "ACL/Ruch wchodzący.md",
    "ACL/Standardowe ACL.md",
    "ACL/Zabezpieczanie portów VTY.md",
    "ACL/Ruch wychodzący.md",
    "Pasted image 20250512173320.png",
    "ACL/Lista ACL.md",
    "Pasted image 20250512172434.png",
    "Pasted image 20250509164029.png",
    "Pasted image 20250509163935.png",
    "Pasted image 20250509163427.png",
    "Jednoobszarowy OSPF/Maska blankietowa.md",
    "QoS/QoS.md",
    "QoS",
    "Jednoobszarowy OSPF/Stany operacyjne OSPF.md",
    "Cyberbezpieczeństwo/nie chce mi sie tego opisywac bo bylo na podstawach cyberbezpieczenstwa w wiekszosci.md",
    "Cyberbezpieczeństwo/Ataki.md",
    "Cyberbezpieczeństwo/Terminologia.md",
    "Cyberbezpieczeństwo/Narzędzia.md",
    "Jednoobszarowy OSPF/Propagowanie trasy domyślnej.md",
    "ACL",
    "Cyberbezpieczeństwo",
    "Jednoobszarowy OSPF/Proces routingu stanu łącza.md",
    "Jednoobszarowy OSPF/OSPF.md",
    "Jednoobszarowy OSPF/Obszary OSPF.md",
    "Jednoobszarowy OSPF/Koszt routingu.md",
    "Jednoobszarowy OSPF/Konfiguracja OSPF.md",
    "Jednoobszarowy OSPF/Komunikaty, pakiety OSPF.md",
    "Jednoobszarowy OSPF"
  ]
}